{
  "id": 459,
  "title": "Best AI Code Tools for Data Science in 2026",
  "slug": "best-ai-code-tools-data-science-2026",
  "date": "2026-05-29",
  "description": "Best AI Code Tools for Data Science in 2026 - Complete guide covering the best tools, tips, and workflows for code with AI in 2026.",
  "style": "沉稳技术风",
  "images": [
    {
      "url": "https://images.unsplash.com/photo-1531297484001-80022131f5a1?w=800&h=400&fit=crop",
      "alt": "Best AI Code Tools for Data Science in 2026",
      "caption": "Comprehensive guide to code with AI"
    },
    {
      "url": "https://images.unsplash.com/photo-1605379399642-870262d19d55?w=800&h=400&fit=crop",
      "alt": "Best AI Code Tools for Data Science in 2026 in action",
      "caption": "See how the tools work in real workflows"
    },
    {
      "url": "https://images.unsplash.com/photo-1607799279861-4dd421887fc3?w=800&h=400&fit=crop",
      "alt": "Start with code",
      "caption": "Get started today with the recommended tools"
    }
  ],
  "content": "# Best AI Code Tools for Data Science in 2026\n\nData science workflows have been transformed by AI coding assistants. From data cleaning to model building, AI code tools save data scientists hours every week.\n\nIn this guide, we explore the best AI code tools for data science in 2026.\n\n---\n\n## AI in Data Science Workflows\n\nThe modern data science workflow benefits from AI at every step:\n- 🧹 **Data cleaning** - AI suggests fixes automatically\n- 📊 **Exploratory analysis** - AI generates visualizations\n- 🤖 **Model building** - AI writes and optimizes models\n- 📝 **Documentation** - AI explains code in plain English\n\n---\n\n## Top AI Code Tools for Data Science\n\n### 1. GitHub Copilot X\n[[link:/tools/79|Copilot]] X brings advanced AI assistance to data scientists.\n\n**Data science superpowers:**\n- 🐼 **Pandas code generation** - Perfect for data manipulation\n- 📊 **Matplotlib/Seaborn** - Beautiful visualizations instantly\n- 🤖 **Scikit-learn pipelines** - Build models in seconds\n- 🔍 **Explain AI** - Understand what your code does\n\n### 2. Codeium\n[[link:/tools/95|Codeium]] offers free, powerful AI coding for data scientists on any budget.\n\n**Best features:**\n- 🆓 **Free for individuals** - Great for students\n- 🐍 **Python-first** - Perfect for data science\n- 📓 **Notebook support** - Works in Jupyter and Colab\n- 🔄 **Real-time suggestions** - As you type\n\n### 3. Amazon CodeWhisperer\n[[link:/tools/94|CodeWhisperer]] excels at AWS-integrated data science workflows.\n\n**AWS integration:**\n- ☁️ **SageMaker code** - Build ML models on AWS\n- 🗄️ **Athena/Redshift** - Query data with AI assistance\n- 🔐 **Security scanning** - Find vulnerabilities in code\n\n---\n\n## Comparison Table\n\n| Tool | Pandas | ML | Notebooks | AWS | Price |\n|------|--------|----|-----------|-----|-------|\n| [[link:/tools/79|Copilot]] | 5/5 | 5/5 | 5/5 | 4/5 | $10/mo |\n| [[link:/tools/95|Codeium]] | 4.5/5 | 4/5 | 4/5 | 3/5 | Free |\n| [[link:/tools/94|CodeWhisperer]] | 4/5 | 4.5/5 | 3/5 | 5/5 | Free/$19 |\n\n---\n\n## Data Science Workflow with AI\n\n1. **Data loading** - AI writes your import/clean code\n2. **Exploration** - Generate visualizations with prompts\n3. **Model building** - AI suggests and implements models\n4. **Evaluation** - AI analyzes results and suggests improvements\n5. **Deployment** - AI writes production-ready code\n\n---\n\n## Final Recommendations\n\n**For most data scientists:** [[link:/tools/79|GitHub Copilot X]] is worth every penny.\n\n**For students/budget:** [[link:/tools/95|Codeium]] free tier is excellent.\n\nSupercharge your data science workflow today!",
  "category": "Code"
}
