{
  "id": 580,
  "title": "5 AI Tools for Email Campaign Writing That Boost Open Rates",
  "slug": "ai-tools-email-campaign-writing-2026",
  "date": "2026-05-31",
  "description": "Discover 5 AI tools for email campaign writing in 2026. Generate high-converting subject lines, body copy, and A/B variants that boost open and click rates.",
  "style": "沉稳技术风",
  "images": [
    {
      "url": "https://images.unsplash.com/photo-1780300213456-jncdaa?w=800&h=400&fit=crop",
      "alt": "5 AI Tools for Email Campaign Writing That Boost Open Rates",
      "caption": "5 AI Tools for Email Campaign Writing That Boost Open Rates"
    }
  ],
  "content": "# 5 AI Tools for Email Campaign Writing That Boost Open Rates\n\nEmail marketing remains one of the highest-ROI digital channels, with every dollar spent returning an average of $36. But the difference between a campaign that converts and one that gets deleted comes down to copy quality. AI writing tools now generate subject lines, body copy, and A/B variants that consistently outperform manually written emails.\n\nExplore more tools in our [[link:/category/Writing|Writing category]].\n\n---\n\n## Why AI Writing Tools Outperform Manual Email Copy\n\nThe advantage of AI in email writing is not just speed — it is data-driven optimization. AI tools analyze millions of email campaigns to understand which subject line patterns drive opens, which body copy structures drive clicks, and which CTAs drive conversions. This collective intelligence produces copy that is optimized from the start, rather than requiring multiple rounds of testing to find what works.\n\nAI also excels at personalization at scale. Instead of writing one email for your entire list, AI tools can generate dozens of variations tailored to different segments — new subscribers, active users, lapsed customers, high-value buyers — each with language that resonates with their specific relationship to your brand.\n\n---\n\n## [[link:/tools/1077|EmailForge AI]] — Purpose-Built Email Campaign Writer\n\nEmailForge AI is designed specifically for email marketing. It generates subject lines with built-in A/B testing variants, audience-segmented body copy, and CTA optimization based on industry benchmarks. The platform understands email-specific constraints — character limits for subject lines, preview text optimization, and mobile-first formatting.\n\nThe tool's subject line engine is its standout feature. It generates multiple variants ranked by predicted open rate, with explanations for why each variant is expected to perform well. This gives marketers data-backed confidence in their subject line choices rather than relying on gut instinct.\n\n**Best for:** Email marketers who need a dedicated tool for campaign copy generation with built-in optimization.\n\n---\n\n## [[link:/tools/23|Rytr]] — Versatile AI Writing Assistant\n\n**Try Rytr Free** — it is one of the most accessible AI writing tools for email marketers. Rytr generates email copy across multiple tones and formats, from promotional campaigns to transactional messages to re-engagement sequences. Its tone adjustment feature lets you match your brand voice precisely, whether that is professional, casual, or playful.\n\nRytr's strength for email marketing is its versatility. The same tool handles subject lines, body copy, preview text, and CTA variations. Its built-in plagiarism checker ensures originality, and its SEO mode helps when emails double as blog content or landing page copy.\n\n**Best for:** Email marketers who want a versatile writing assistant that handles multiple content types beyond just email.\n\n---\n\n## [[link:/tools/90|GrammarlyGO]] — AI-Powered Copy Refinement\n\n**Try GrammarlyGO Free** — it transforms rough email drafts into polished, persuasive copy. While other tools generate from scratch, GrammarlyGO excels at refining existing copy — adjusting tone, improving clarity, strengthening CTAs, and ensuring grammatical perfection. This makes it ideal for marketers who have a message but need help expressing it effectively.\n\nGrammarlyGO's tone detection is particularly valuable for email. It analyzes your draft and identifies whether it sounds confident, friendly, urgent, or formal — then lets you adjust the tone with a single click. This ensures your email campaigns maintain consistent brand voice across all touchpoints.\n\n**Best for:** Marketers who draft their own emails and need AI assistance to refine tone, clarity, and persuasiveness.\n\n---\n\n## [[link:/tools/1090|EmailSequence AI]] — Drip Campaign Builder\n\nEmailSequence AI specializes in multi-email sequences — onboarding drips, nurture campaigns, re-engagement flows, and post-purchase follow-ups. Its AI generates entire sequence architectures with behavioral trigger logic, timing optimization, and conversion funnel alignment.\n\nThe platform understands that email sequences are not just individual emails — they are conversations that build over time. Its AI ensures each email in a sequence builds on the previous one, maintaining narrative continuity while driving toward a conversion goal. This holistic approach produces sequences that convert significantly better than individually written emails.\n\n**Best for:** SaaS companies and e-commerce brands that rely on automated email sequences for onboarding and retention.\n\n---\n\n## [[link:/tools/1080|AdCopyForge AI]] — Promotional Email Specialist\n\nAdCopyForge AI generates promotional email copy with the same precision it brings to paid advertising. It understands the psychology of urgency, scarcity, and social proof — and applies these principles to email campaigns that drive immediate action. Its compliance checking ensures promotional language meets CAN-SPAM and GDPR requirements.\n\nThe tool's performance prediction scoring estimates how well each email variant will perform before you send it. This pre-send optimization reduces the risk of underperforming campaigns and helps marketers allocate send volume to the strongest variants.\n\n**Best for:** Marketers running promotional email campaigns that need to drive immediate purchases or sign-ups.\n\n---\n\n## Comparison Table\n\n| Tool | Primary Focus | Pricing | Best For |\n|------|--------------|---------|----------|\n| EmailForge AI | Email campaign writing | Freemium | Dedicated email copy |\n| Rytr | Versatile writing | Freemium | Multi-format copy |\n| GrammarlyGO | Copy refinement | Freemium | Tone and clarity |\n| EmailSequence AI | Drip campaigns | Paid | Automated sequences |\n| AdCopyForge AI | Promotional copy | Freemium | Sales-driven emails |\n\n---\n\n## How to Choose\n\nFor dedicated email campaign writing, **EmailForge AI** is the primary tool. **Rytr** provides versatile writing across formats. **GrammarlyGO** refines existing drafts for tone and clarity. For automated sequences, **EmailSequence AI** handles the full drip campaign architecture. For promotional urgency, **AdCopyForge AI** drives immediate action.\n\n---\n\n## Conclusion\n\nEmail marketing success starts with great copy, and AI tools make great copy accessible to every marketer. Start with **Rytr** for versatile writing and **GrammarlyGO** for refinement — both offer free tiers that deliver immediate value. Then add **EmailForge AI** for campaign-specific optimization and **EmailSequence AI** for automated flows. Explore more writing tools in our [[link:/category/Writing|Writing category]].",
  "category": "Writing",
  "author": "Use AI Tools Team"
}