{
  "id": 606,
  "title": "5 AI Tools for TikTok Ads Video Creation and Trend Matching",
  "slug": "ai-tools-tiktok-ads-video-creation-2026",
  "date": "2026-05-31",
  "description": "Discover 5 AI tools for TikTok ads video in 2026. Create trend-matching ad creatives with music sync and performance prediction for high-converting ads.",
  "style": "沉稳技术风",
  "images": [
    {
      "url": "https://images.unsplash.com/photo-1780300213460-hld6fk?w=800&h=400&fit=crop",
      "alt": "5 AI Tools for TikTok Ads Video Creation and Trend Matching",
      "caption": "5 AI Tools for TikTok Ads Video Creation and Trend Matching"
    }
  ],
  "content": "# 5 AI Tools for TikTok Ads Video Creation and Trend Matching\n\nTikTok advertising is fundamentally different from other platforms. Ads that look like ads get scrolled past. The most effective TikTok ads look like organic content — they use trending sounds, match current visual styles, and feel native to the platform. AI tools that understand TikTok's creative culture give you the authenticity advantage that drives conversions.\n\nExplore more tools in our [[link:/category/Video|Video category]].\n\n---\n\n## The TikTok Ads Creative Challenge\n\nTikTok's algorithm rewards content that feels authentic and engaging. Ads that are too polished or obviously promotional underperform compared to content that matches the platform's creative energy. This creates a tension for advertisers: you need professional results with amateur authenticity. AI tools resolve this tension by generating content that is both effective and native-feeling.\n\nThe trend cycle on TikTok is incredibly fast. A trending sound or visual style can emerge and fade within days. AI tools monitor these trends in real time and generate ad creative that matches current styles before they expire. This speed-to-trend capability is impossible with traditional ad production.\n\n---\n\n## [[link:/tools/1010|TikTok Ads Pro]] — TikTok Ad Creation Suite\n\nTikTok Ads Pro is purpose-built for TikTok advertising. It generates trend-matching ad templates, synchronizes video cuts with trending music, and predicts ad performance before you launch. Its AI monitors TikTok's creative trends and generates ad concepts that align with current styles.\n\nThe platform's music synchronization feature is its standout capability. It analyzes trending TikTok sounds and automatically synchronizes your video cuts to the beat, creating the rhythmic editing style that performs best on TikTok. This music-video synchronization is technically difficult to do manually but comes naturally to the AI.\n\n**Best for:** Brands running TikTok ad campaigns who need trend-native creative at speed.\n\n---\n\n## [[link:/tools/51|VEED.io]] — TikTok Video Editing\n\n**Try VEED.io Free** — it provides TikTok-specific editing features including vertical video formatting, auto-captions, and trend-aware effects. Its AI generates captions in the bold, colorful style that performs best on TikTok, and its effects library includes the transitions and filters currently trending on the platform.\n\nFor TikTok ads specifically, VEED.io's hook generator creates compelling first-3-second openings that prevent scrolling. Its CTA overlay feature adds clickable elements that drive conversions without disrupting the native-feeling creative.\n\n**Best for:** Creating and editing TikTok ad videos with platform-native features and effects.\n\n---\n\n## [[link:/tools/201|Pictory]] — Long-Form to TikTok Clip Conversion\n\n**Try Pictory Free** — it transforms long-form video content into TikTok-optimized clips. Its AI identifies the most engaging 15-60 second segments from webinars, product demos, and testimonials, then formats them with vertical aspect ratio, captions, and trending-style editing.\n\nFor brands with existing video content, Pictory provides a cost-effective way to produce TikTok ads without shooting new footage. The AI's segment selection is remarkably accurate at identifying shareable moments.\n\n**Best for:** Repurposing existing video content into TikTok ad clips.\n\n---\n\n## [[link:/tools/987|TikTokGenius AI]] — Trend Intelligence and Content Strategy\n\nTikTokGenius AI provides the trend intelligence that informs your TikTok ad strategy. It monitors trending sounds, hashtags, visual styles, and creator content in real time, identifying opportunities for ad creative that will feel current and authentic. Its AI generates trend-adapted content suggestions with TikTok-specific formatting.\n\nThe tool's trend prediction feature identifies emerging trends before they peak, giving you a head start on creative development. This predictive capability is invaluable for brands that want to lead trends rather than follow them.\n\n**Best for:** Strategic trend monitoring and content planning for TikTok advertising.\n\n---\n\n## [[link:/tools/1011|VidRepurpose AI]] — Multi-Platform TikTok Distribution\n\nVidRepurpose AI adapts your TikTok ads for distribution across other short-form platforms — Instagram Reels, YouTube Shorts, and Snapchat Spotlight. Each platform has different technical requirements and audience expectations, and the AI handles the reformatting automatically.\n\nThe tool also generates platform-specific descriptions, hashtags, and posting time recommendations, ensuring your TikTok-optimized creative performs well across your entire short-form video strategy.\n\n**Best for:** Distributing TikTok ad creative across multiple short-form video platforms.\n\n---\n\n## Comparison Table\n\n| Tool | Primary Focus | Pricing | Best For |\n|------|--------------|---------|----------|\n| TikTok Ads Pro | TikTok ad creation | Freemium | Trend-native ads |\n| VEED.io | Video editing | Freemium | TikTok editing |\n| Pictory | Content repurposing | Freemium | Long-form to TikTok |\n| TikTokGenius AI | Trend intelligence | Freemium | Trend monitoring |\n| VidRepurpose AI | Multi-platform | Freemium | Cross-platform distribution |\n\n---\n\n## How to Choose\n\n**TikTok Ads Pro** for dedicated TikTok ad creation with trend matching. **VEED.io** for editing and effects. **Pictory** for repurposing existing content. **TikTokGenius AI** for trend intelligence. **VidRepurpose AI** for multi-platform distribution.\n\n---\n\n## Conclusion\n\nTikTok advertising demands creative that matches the platform's unique culture. These five AI tools cover the full TikTok ads pipeline from trend monitoring to creative production to multi-platform distribution. Start with **VEED.io** and **Pictory** for content creation, then add **TikTok Ads Pro** for trend-native ad production. Explore more in our [[link:/category/Video|Video category]].",
  "category": "Video"
}
