{
  "id": 650,
  "title": "How to Create AI-Generated Real Estate Tours in 2026",
  "slug": "how-to-create-ai-generated-real-estate-tours-2026-650",
  "date": "2026-06-01",
  "category": "Video",
  "description": "Learn how to create AI-generated real estate tours in 2026. Step-by-step guide to producing professional virtual property tours with AI-powered tools.",
  "content": "# How to Create AI-Generated Real Estate Tours in 2026\n\nFinding the right AI tools for video can be overwhelming. The market is flooded with options, each claiming to be the best. But which ones actually deliver results?\n\nWe've tested and reviewed the top AI video tools for video in 2026. Whether you're a beginner or a seasoned professional, these tools will save you time and boost your output.\n\nExplore more tools in our [[link:/category/video|Video AI Tools]] category.\n\n---\n\n## Why AI Tools Matter for Video\n\nThe landscape of video has changed dramatically with AI. Tasks that once took hours now take minutes. Creative blocks are broken with AI-generated ideas. And the quality gap between amateurs and professionals is narrowing every day.\n\nHere's what AI video tools can do for your video workflow:\n\n- **Automate repetitive tasks** so you can focus on creative decisions\n- **Generate professional-quality output** without years of training\n- **Scale your production** without proportionally scaling your team\n- **Discover new possibilities** that you might never have considered\n\n---\n\n## PropertyTour AI\n\nCreate professional real estate virtual tours with AI-powered 360-degree video stitching, automated room labeling, and interactive floor plan integration.\n\n**Key features:**\n\n- Advanced AI-powered video capabilities\n- Intuitive interface designed for video\n- Real-time processing and instant results\n- Integration with popular video platforms\n- Collaborative features for team workflows\n\n**Pricing:** Freemium\n\n**Best for:** Virtual Tours, 360-Degree Video, Floor Plan Integration\n\n---\n\n## RealEstateVid AI\n\nAI real estate video generator that creates property walkthroughs, neighborhood highlights, and market analysis videos from property listing data.\n\n**Key features:**\n\n- Advanced AI-powered video capabilities\n- Intuitive interface designed for video\n- Real-time processing and instant results\n- Integration with popular video platforms\n- Collaborative features for team workflows\n\n**Pricing:** Paid\n\n**Best for:** Property Walkthroughs, Neighborhood Highlights, Market Analysis\n\n---\n\n## HomeTour Pro AI\n\nAI-powered real estate video production with drone footage integration, automated staging overlays, and multilingual narration for international property marketing.\n\n**Key features:**\n\n- Advanced AI-powered video capabilities\n- Intuitive interface designed for video\n- Real-time processing and instant results\n- Integration with popular video platforms\n- Collaborative features for team workflows\n\n**Pricing:** Freemium\n\n**Best for:** Drone Integration, Virtual Staging, Multilingual Narration\n\n---\n\n## ListingsVideo AI\n\nTransform real estate photos into engaging video tours with AI. Creates smooth transitions, adds ambient music, and generates property description voice-overs.\n\n**Key features:**\n\n- Advanced AI-powered video capabilities\n- Intuitive interface designed for video\n- Real-time processing and instant results\n- Integration with popular video platforms\n- Collaborative features for team workflows\n\n**Pricing:** Freemium\n\n**Best for:** Photo to Video, Smooth Transitions, Description Voice-Over\n\n---\n\n## AgentReel AI\n\nAI video marketing tool for real estate agents that creates branded property videos, market update content, and client testimonial compilations.\n\n**Key features:**\n\n- Advanced AI-powered video capabilities\n- Intuitive interface designed for video\n- Real-time processing and instant results\n- Integration with popular video platforms\n- Collaborative features for team workflows\n\n**Pricing:** Paid\n\n**Best for:** Branded Videos, Market Updates, Testimonial Compilations\n\n---\n\n## Comparison Table\n\n| Tool | Pricing | Key Strength | Best For |\n|------|---------|-------------|----------|\n| PropertyTour AI | Freemium | 360-Degree Video | Virtual Tours |\n| RealEstateVid AI | Paid | Neighborhood Highlights | Property Walkthroughs |\n| HomeTour Pro AI | Freemium | Virtual Staging | Drone Integration |\n| ListingsVideo AI | Freemium | Smooth Transitions | Photo to Video |\n| AgentReel AI | Paid | Market Updates | Branded Videos |\n\n---\n\n## How to Choose the Right Tool\n\nChoosing the right AI video tool for video depends on your specific needs:\n\n1. **Define your primary use case** — Are you creating content, automating workflows, or analyzing data?\n2. **Consider your budget** — Free tools work for getting started, but paid tools offer more advanced features\n3. **Test before committing** — Most tools offer free trials or free tiers\n4. **Check integration options** — Make sure the tool works with your existing workflow\n5. **Read user reviews** — Real user feedback reveals strengths and weaknesses\n\n---\n\n## Conclusion\n\nAI video tools for video have matured significantly in 2026. Whether you choose **PropertyTour AI** for its comprehensive features or **RealEstateVid AI** for its specialized capabilities, you'll see immediate improvements in your workflow.\n\nStart with a free trial, test the features that matter most to you, and upgrade when you're ready. The right AI tool can transform your video from time-consuming to effortless.\n\nExplore more options in our [[link:/category/video|Video AI Tools]] directory.\n",
  "featured": false,
  "author": "Use AI Tools Team",
  "reading_time": "10 min",
  "thumbnail": "",
  "images": [],
  "canonical_slug": "how-to-create-ai-generated-real-estate-tours-2026"
}
